onnx_shape_fix/__init__.py
onnx_shape_fix/cli.py
onnx_shape_fix/propagator.py
onnx_shape_fix/batch/__init__.py
onnx_shape_fix/batch/bn_tracker.py
onnx_shape_fix/batch/remover.py
onnx_shape_fix/batch/tracker.py
onnx_shape_fix/handlers/__init__.py
onnx_shape_fix/handlers/base_handler.py
onnx_shape_fix/handlers/elementwise.py
onnx_shape_fix/handlers/flow_ops.py
onnx_shape_fix/handlers/math_ops.py
onnx_shape_fix/handlers/nn_ops.py
onnx_shape_fix/handlers/shape_ops.py
onnx_shape_fix/utils/__init__.py
onnx_shape_fix/utils/constant_utils.py
onnx_shape_fix/utils/logger.py
onnx_shape_fix/utils/onnx_shape_infer.py
onnx_shape_fix-0.2.1.dist-info/METADATA
onnx_shape_fix-0.2.1.dist-info/WHEEL
onnx_shape_fix-0.2.1.dist-info/entry_points.txt
onnx_shape_fix-0.2.1.dist-info/top_level.txt
onnx_shape_fix-0.2.1.dist-info/RECORD
