Metadata-Version: 2.4
Name: onnx-shape-fix
Version: 0.2.1
Summary: A tool to fix shape information in ONNX models
Home-page: https://github.com/hafizabc77/onnx-shape-fix
Author: Hafiz
Author-email: hafizabc77@gmail.com
Classifier: Development Status :: 3 - Alpha
Classifier: Intended Audience :: Developers
Classifier: Intended Audience :: Science/Research
Classifier: License :: OSI Approved :: MIT License
Classifier: Programming Language :: Python :: 3
Classifier: Programming Language :: Python :: 3.7
Classifier: Programming Language :: Python :: 3.8
Classifier: Programming Language :: Python :: 3.9
Classifier: Topic :: Scientific/Engineering
Classifier: Topic :: Scientific/Engineering :: Artificial Intelligence
Requires-Python: >=3.7
Requires-Dist: onnx>=1.12.0
Requires-Dist: numpy>=1.19.0
Requires-Dist: protobuf<4.0.0,>=3.20.0
Dynamic: author
Dynamic: author-email
Dynamic: classifier
Dynamic: description
Dynamic: description-content-type
Dynamic: home-page
Dynamic: requires-dist
Dynamic: requires-python
Dynamic: summary
